{
    "LilyPadUSB": {
        "build": {
            "core": "arduino",
            "extra_flags": "-DARDUINO_ARCH_AVR -DARDUINO_AVR_LILYPAD_USB",
            "f_cpu": "8000000L",
            "mcu": "atmega32u4",
            "pid": "0x9208",
            "usb_product": "LilyPad USB",
            "variant": "leonardo",
            "vid": "0x1B4F"
        },
        "framework": "arduino",
        "name": "LilyPad Arduino USB",
        "platform": "atmelavr",
        "upload": {
            "disable_flushing": true,
            "maximum_ram_size": 2560,
            "maximum_size": 28672,
            "protocol": "avr109",
            "require_upload_port" : true,
            "speed": 57600,
            "use_1200bps_touch": true,
            "wait_for_upload_port": true
        }
    },
    "atmegangatmega168": {
        "build": {
            "core": "arduino",
            "extra_flags": "-DARDUINO_ARCH_AVR -DARDUINO_AVR_NG",
            "f_cpu": "16000000L",
            "mcu": "atmega168",
            "variant": "standard"
        },
        "framework": "arduino",
        "name": "Arduino NG or older ATmega168",
        "platform": "atmelavr",
        "upload": {
            "maximum_ram_size": 1024,
            "maximum_size": 14336,
            "protocol": "arduino",
            "require_upload_port" : true,
            "speed": 19200
        }
    },
    "atmegangatmega8": {
        "build": {
            "core": "arduino",
            "extra_flags": "-DARDUINO_ARCH_AVR -DARDUINO_AVR_NG",
            "f_cpu": "16000000L",
            "mcu": "atmega8",
            "variant": "standard"
        },
        "framework": "arduino",
        "name": "Arduino NG or older ATmega8",
        "platform": "atmelavr",
        "upload": {
            "maximum_ram_size": 1024,
            "maximum_size": 7168,
            "protocol": "arduino",
            "require_upload_port" : true,
            "speed": 19200
        }
    },
    "btatmega168": {
        "build": {
            "core": "arduino",
            "extra_flags": "-DARDUINO_ARCH_AVR -DARDUINO_AVR_BT",
            "f_cpu": "16000000L",
            "mcu": "atmega168",
            "variant": "eightanaloginputs"
        },
        "framework": "arduino",
        "name": "Arduino BT ATmega168",
        "platform": "atmelavr",
        "upload": {
            "disable_flushing": true,
            "maximum_ram_size": 1024,
            "maximum_size": 14336,
            "protocol": "arduino",
            "require_upload_port" : true,
            "speed": 19200
        }
    },
    "btatmega328": {
        "build": {
            "core": "arduino",
            "extra_flags": "-DARDUINO_ARCH_AVR -DARDUINO_AVR_BT",
            "f_cpu": "16000000L",
            "mcu": "atmega328p",
            "variant": "eightanaloginputs"
        },
        "framework": "arduino",
        "name": "Arduino BT ATmega328",
        "platform": "atmelavr",
        "upload": {
            "disable_flushing": true,
            "maximum_ram_size": 2048,
            "maximum_size": 28672,
            "protocol": "arduino",
            "require_upload_port" : true,
            "speed": 19200
        }
    },
    "diecimilaatmega168": {
        "build": {
            "core": "arduino",
            "extra_flags": "-DARDUINO_ARCH_AVR -DARDUINO_AVR_DUEMILANOVE",
            "f_cpu": "16000000L",
            "mcu": "atmega168",
            "variant": "standard"
        },
        "framework": "arduino",
        "name": "Arduino Duemilanove or Diecimila ATmega168",
        "platform": "atmelavr",
        "upload": {
            "maximum_ram_size": 1024,
            "maximum_size": 14336,
            "protocol": "arduino",
            "require_upload_port" : true,
            "speed": 19200
        }
    },
    "diecimilaatmega328": {
        "build": {
            "core": "arduino",
            "extra_flags": "-DARDUINO_ARCH_AVR -DARDUINO_AVR_DUEMILANOVE",
            "f_cpu": "16000000L",
            "mcu": "atmega328p",
            "variant": "standard"
        },
        "framework": "arduino",
        "name": "Arduino Duemilanove or Diecimila ATmega328",
        "platform": "atmelavr",
        "upload": {
            "maximum_ram_size": 2048,
            "maximum_size": 30720,
            "protocol": "arduino",
            "require_upload_port" : true,
            "speed": 57600
        }
    },
    "esplora": {
        "build": {
            "core": "arduino",
            "extra_flags": "-DARDUINO_ARCH_AVR -DARDUINO_AVR_ESPLORA",
            "f_cpu": "16000000L",
            "mcu": "atmega32u4",
            "pid": "0x803c",
            "usb_product": "Arduino Esplora",
            "variant": "leonardo",
            "vid": "0x2341"
        },
        "framework": "arduino",
        "name": "Arduino Esplora",
        "platform": "atmelavr",
        "upload": {
            "disable_flushing": true,
            "maximum_ram_size": 2560,
            "maximum_size": 28672,
            "protocol": "avr109",
            "require_upload_port" : true,
            "speed": 57600,
            "use_1200bps_touch": true,
            "wait_for_upload_port": true
        }
    },
    "ethernet": {
        "build": {
            "core": "arduino",
            "extra_flags": "-DARDUINO_ARCH_AVR -DARDUINO_AVR_ETHERNET",
            "f_cpu": "16000000L",
            "mcu": "atmega328p",
            "variant": "ethernet"
        },
        "framework": "arduino",
        "name": "Arduino Ethernet",
        "platform": "atmelavr",
        "upload": {
            "maximum_ram_size": 2048,
            "maximum_size": 32256,
            "protocol": "arduino",
            "require_upload_port" : true,
            "speed": 115200
        }
    },
    "fio": {
        "build": {
            "core": "arduino",
            "extra_flags": "-DARDUINO_ARCH_AVR -DARDUINO_AVR_FIO",
            "f_cpu": "8000000L",
            "mcu": "atmega328p",
            "variant": "eightanaloginputs"
        },
        "framework": "arduino",
        "name": "Arduino Fio",
        "platform": "atmelavr",
        "upload": {
            "maximum_ram_size": 2048,
            "maximum_size": 30720,
            "protocol": "arduino",
            "require_upload_port" : true,
            "speed": 57600
        }
    },
    "leonardo": {
        "build": {
            "core": "arduino",
            "extra_flags": "-DARDUINO_ARCH_AVR -DARDUINO_AVR_LEONARDO",
            "f_cpu": "16000000L",
            "mcu": "atmega32u4",
            "pid": "0x8036",
            "usb_product": "Arduino Leonardo",
            "variant": "leonardo",
            "vid": "0x2341"
        },
        "framework": "arduino",
        "name": "Arduino Leonardo",
        "platform": "atmelavr",
        "upload": {
            "disable_flushing": true,
            "maximum_ram_size": 2560,
            "maximum_size": 28672,
            "protocol": "avr109",
            "require_upload_port" : true,
            "speed": 57600,
            "use_1200bps_touch": true,
            "wait_for_upload_port": true
        }
    },
    "lilypadatmega168": {
        "build": {
            "core": "arduino",
            "extra_flags": "-DARDUINO_ARCH_AVR -DARDUINO_AVR_LILYPAD",
            "f_cpu": "8000000L",
            "mcu": "atmega168",
            "variant": "standard"
        },
        "framework": "arduino",
        "name": "LilyPad Arduino ATmega168",
        "platform": "atmelavr",
        "upload": {
            "maximum_ram_size": 1024,
            "maximum_size": 14336,
            "protocol": "arduino",
            "require_upload_port" : true,
            "speed": 19200
        }
    },
    "lilypadatmega328": {
        "build": {
            "core": "arduino",
            "extra_flags": "-DARDUINO_ARCH_AVR -DARDUINO_AVR_LILYPAD",
            "f_cpu": "8000000L",
            "mcu": "atmega328p",
            "variant": "standard"
        },
        "framework": "arduino",
        "name": "LilyPad Arduino ATmega328",
        "platform": "atmelavr",
        "upload": {
            "maximum_ram_size": 2048,
            "maximum_size": 30720,
            "protocol": "arduino",
            "require_upload_port" : true,
            "speed": 57600
        }
    },
    "megaADK": {
        "build": {
            "core": "arduino",
            "extra_flags": "-DARDUINO_ARCH_AVR -DARDUINO_AVR_ADK",
            "f_cpu": "16000000L",
            "mcu": "atmega2560",
            "variant": "mega"
        },
        "framework": "arduino",
        "name": "Arduino Mega ADK",
        "platform": "atmelavr",
        "upload": {
            "maximum_ram_size": 8192,
            "maximum_size": 253952,
            "protocol": "wiring",
            "require_upload_port" : true,
            "speed": 115200
        }
    },
    "megaatmega1280": {
        "build": {
            "core": "arduino",
            "extra_flags": "-DARDUINO_ARCH_AVR -DARDUINO_AVR_MEGA",
            "f_cpu": "16000000L",
            "mcu": "atmega1280",
            "variant": "mega"
        },
        "framework": "arduino",
        "name": "Arduino Mega or Mega 2560 ATmega1280",
        "platform": "atmelavr",
        "upload": {
            "maximum_ram_size": 8192,
            "maximum_size": 126976,
            "protocol": "arduino",
            "require_upload_port" : true,
            "speed": 57600
        }
    },
    "megaatmega2560": {
        "build": {
            "core": "arduino",
            "extra_flags": "-DARDUINO_ARCH_AVR -DARDUINO_AVR_MEGA2560",
            "f_cpu": "16000000L",
            "mcu": "atmega2560",
            "variant": "mega"
        },
        "framework": "arduino",
        "name": "Arduino Mega or Mega 2560 ATmega2560 (Mega 2560)",
        "platform": "atmelavr",
        "upload": {
            "maximum_ram_size": 8192,
            "maximum_size": 253952,
            "protocol": "wiring",
            "require_upload_port" : true,
            "speed": 115200
        }
    },
    "micro": {
        "build": {
            "core": "arduino",
            "extra_flags": "-DARDUINO_ARCH_AVR -DARDUINO_AVR_MICRO",
            "f_cpu": "16000000L",
            "mcu": "atmega32u4",
            "pid": "0x8037",
            "usb_product": "Arduino Micro",
            "variant": "micro",
            "vid": "0x2341"
        },
        "framework": "arduino",
        "name": "Arduino Micro",
        "platform": "atmelavr",
        "upload": {
            "disable_flushing": true,
            "maximum_ram_size": 2560,
            "maximum_size": 28672,
            "protocol": "avr109",
            "require_upload_port" : true,
            "speed": 57600,
            "use_1200bps_touch": true,
            "wait_for_upload_port": true
        }
    },
    "miniatmega168": {
        "build": {
            "core": "arduino",
            "extra_flags": "-DARDUINO_ARCH_AVR -DARDUINO_AVR_MINI",
            "f_cpu": "16000000L",
            "mcu": "atmega168",
            "variant": "eightanaloginputs"
        },
        "framework": "arduino",
        "name": "Arduino Mini ATmega168",
        "platform": "atmelavr",
        "upload": {
            "maximum_ram_size": 1024,
            "maximum_size": 14336,
            "protocol": "arduino",
            "require_upload_port" : true,
            "speed": 19200
        }
    },
    "miniatmega328": {
        "build": {
            "core": "arduino",
            "extra_flags": "-DARDUINO_ARCH_AVR -DARDUINO_AVR_MINI",
            "f_cpu": "16000000L",
            "mcu": "atmega328p",
            "variant": "eightanaloginputs"
        },
        "framework": "arduino",
        "name": "Arduino Mini ATmega328",
        "platform": "atmelavr",
        "upload": {
            "maximum_ram_size": 2048,
            "maximum_size": 28672,
            "protocol": "arduino",
            "require_upload_port" : true,
            "speed": 115200
        }
    },
    "nanoatmega168": {
        "build": {
            "core": "arduino",
            "extra_flags": "-DARDUINO_ARCH_AVR -DARDUINO_AVR_NANO",
            "f_cpu": "16000000L",
            "mcu": "atmega168",
            "variant": "eightanaloginputs"
        },
        "framework": "arduino",
        "name": "Arduino Nano ATmega168",
        "platform": "atmelavr",
        "upload": {
            "maximum_ram_size": 1024,
            "maximum_size": 14336,
            "protocol": "arduino",
            "require_upload_port" : true,
            "speed": 19200
        }
    },
    "nanoatmega328": {
        "build": {
            "core": "arduino",
            "extra_flags": "-DARDUINO_ARCH_AVR -DARDUINO_AVR_NANO",
            "f_cpu": "16000000L",
            "mcu": "atmega328p",
            "variant": "eightanaloginputs"
        },
        "framework": "arduino",
        "name": "Arduino Nano ATmega328",
        "platform": "atmelavr",
        "upload": {
            "maximum_ram_size": 2048,
            "maximum_size": 30720,
            "protocol": "arduino",
            "require_upload_port" : true,
            "speed": 57600
        }
    },
    "pro16MHzatmega168": {
        "build": {
            "core": "arduino",
            "extra_flags": "-DARDUINO_ARCH_AVR -DARDUINO_AVR_PRO",
            "f_cpu": "16000000L",
            "mcu": "atmega168",
            "variant": "eightanaloginputs"
        },
        "framework": "arduino",
        "name": "Arduino Pro or Pro Mini ATmega168 (5V, 16 MHz)",
        "platform": "atmelavr",
        "upload": {
            "maximum_ram_size": 1024,
            "maximum_size": 14336,
            "protocol": "arduino",
            "require_upload_port" : true,
            "speed": 19200
        }
    },
    "pro16MHzatmega328": {
        "build": {
            "core": "arduino",
            "extra_flags": "-DARDUINO_ARCH_AVR -DARDUINO_AVR_PRO",
            "f_cpu": "16000000L",
            "mcu": "atmega328p",
            "variant": "eightanaloginputs"
        },
        "framework": "arduino",
        "name": "Arduino Pro or Pro Mini ATmega328 (5V, 16 MHz)",
        "platform": "atmelavr",
        "upload": {
            "maximum_ram_size": 2048,
            "maximum_size": 30720,
            "protocol": "arduino",
            "require_upload_port" : true,
            "speed": 57600
        }
    },
    "pro8MHzatmega168": {
        "build": {
            "core": "arduino",
            "extra_flags": "-DARDUINO_ARCH_AVR -DARDUINO_AVR_PRO",
            "f_cpu": "8000000L",
            "mcu": "atmega168",
            "variant": "eightanaloginputs"
        },
        "framework": "arduino",
        "name": "Arduino Pro or Pro Mini ATmega168 (3.3V, 8 MHz)",
        "platform": "atmelavr",
        "upload": {
            "maximum_ram_size": 1024,
            "maximum_size": 14336,
            "protocol": "arduino",
            "require_upload_port" : true,
            "speed": 19200
        }
    },
    "pro8MHzatmega328": {
        "build": {
            "core": "arduino",
            "extra_flags": "-DARDUINO_ARCH_AVR -DARDUINO_AVR_PRO",
            "f_cpu": "8000000L",
            "mcu": "atmega328p",
            "variant": "eightanaloginputs"
        },
        "framework": "arduino",
        "name": "Arduino Pro or Pro Mini ATmega328 (3.3V, 8 MHz)",
        "platform": "atmelavr",
        "upload": {
            "maximum_ram_size": 2048,
            "maximum_size": 30720,
            "protocol": "arduino",
            "require_upload_port" : true,
            "speed": 57600
        }
    },
    "robotControl": {
        "build": {
            "core": "arduino",
            "extra_flags": "-DARDUINO_ARCH_AVR -DARDUINO_AVR_ROBOT_CONTROL",
            "f_cpu": "16000000L",
            "mcu": "atmega32u4",
            "pid": "0x8038",
            "usb_product": "Robot Control",
            "variant": "robot_control",
            "vid": "0x2341"
        },
        "framework": "arduino",
        "name": "Arduino Robot Control",
        "platform": "atmelavr",
        "upload": {
            "disable_flushing": true,
            "maximum_ram_size": 2560,
            "maximum_size": 28672,
            "protocol": "avr109",
            "require_upload_port" : true,
            "speed": 57600,
            "use_1200bps_touch": true,
            "wait_for_upload_port": true
        }
    },
    "robotMotor": {
        "build": {
            "core": "arduino",
            "extra_flags": "-DARDUINO_ARCH_AVR -DARDUINO_AVR_ROBOT_MOTOR",
            "f_cpu": "16000000L",
            "mcu": "atmega32u4",
            "pid": "0x8039",
            "usb_product": "Robot Motor",
            "variant": "robot_motor",
            "vid": "0x2341"
        },
        "framework": "arduino",
        "name": "Arduino Robot Motor",
        "platform": "atmelavr",
        "upload": {
            "disable_flushing": true,
            "maximum_ram_size": 2560,
            "maximum_size": 28672,
            "protocol": "avr109",
            "require_upload_port" : true,
            "speed": 57600,
            "use_1200bps_touch": true,
            "wait_for_upload_port": true
        }
    },
    "uno": {
        "build": {
            "core": "arduino",
            "extra_flags": "-DARDUINO_ARCH_AVR -DARDUINO_AVR_UNO",
            "f_cpu": "16000000L",
            "mcu": "atmega328p",
            "variant": "standard"
        },
        "framework": "arduino",
        "name": "Arduino Uno",
        "platform": "atmelavr",
        "upload": {
            "maximum_ram_size": 2048,
            "maximum_size": 32256,
            "protocol": "arduino",
            "require_upload_port" : true,
            "speed": 115200
        }
    },
    "yun": {
        "build": {
            "core": "arduino",
            "extra_flags": "-DARDUINO_ARCH_AVR -DARDUINO_AVR_YUN",
            "f_cpu": "16000000L",
            "mcu": "atmega32u4",
            "pid": "0x8041",
            "usb_product": "Arduino Yun",
            "variant": "yun",
            "vid": "0x2341"
        },
        "framework": "arduino",
        "name": "Arduino Yun",
        "platform": "atmelavr",
        "upload": {
            "disable_flushing": true,
            "maximum_ram_size": 2560,
            "maximum_size": 28672,
            "protocol": "avr109",
            "require_upload_port" : true,
            "speed": 57600,
            "use_1200bps_touch": true,
            "via_ssh": true,
            "wait_for_upload_port": true
        }
    },
    "due": {
        "build": {
            "core": "arduino",
            "extra_flags": "-D__SAM3X8E__ -DARDUINO_SAM_DUE -DARDUINO_ARCH_SAM",
            "f_cpu": "84000000L",
            "mcu": "at91sam3x8e",
            "cpu": "cortex-m3",
            "pid": "0x003e",
            "usb_product": "Arduino Due",
            "variant": "arduino_due_x",
            "vid": "0x2341",
            "ldscript": "sam3x8e.ld"
        },
        "framework": "arduino",
        "name": "Arduino Due (Programming Port)",
        "platform": "atmelsam",
        "upload": {
            "disable_flushing": true,
            "maximum_ram_size": 28672,
            "maximum_size": 524288,
            "protocol": "sam-ba",
            "require_upload_port" : true, 
            "use_1200bps_touch": true,
            "wait_for_upload_port": true
        }
    },
    "dueUSB": {
        "build": {
            "core": "arduino",
            "extra_flags": "-D__SAM3X8E__ -DARDUINO_SAM_DUE -DARDUINO_ARCH_SAM",
            "f_cpu": "84000000L",
            "mcu": "at91sam3x8e",
            "cpu": "cortex-m3",
            "pid": "0x003e",
            "usb_product": "Arduino Due",
            "variant": "arduino_due_x",
            "vid": "0x2341",
            "ldscript": "sam3x8e.ld"
        },
        "framework": "arduino",
        "name": "Arduino Due (USB Native Port)",
        "platform": "atmelsam",
        "upload": {
            "disable_flushing": true,
            "maximum_ram_size": 28672,
            "maximum_size": 524288,
            "protocol": "sam-ba",
            "require_upload_port" : true, 
            "use_1200bps_touch": true,
            "wait_for_upload_port": true
        }
    }
}
